odoo/addons/survey_text_question_validation_length/README.rst
odoo/addons/survey_text_question_validation_length/__init__.py
odoo/addons/survey_text_question_validation_length/__manifest__.py
odoo/addons/survey_text_question_validation_length/i18n/it.po
odoo/addons/survey_text_question_validation_length/i18n/survey_text_question_validation_length.pot
odoo/addons/survey_text_question_validation_length/models/__init__.py
odoo/addons/survey_text_question_validation_length/models/survey_question.py
odoo/addons/survey_text_question_validation_length/readme/CONTRIBUTORS.rst
odoo/addons/survey_text_question_validation_length/readme/DESCRIPTION.rst
odoo/addons/survey_text_question_validation_length/static/description/icon.png
odoo/addons/survey_text_question_validation_length/static/description/index.html
odoo/addons/survey_text_question_validation_length/tests/__init__.py
odoo/addons/survey_text_question_validation_length/tests/test_survey_question.py
odoo/addons/survey_text_question_validation_length/views/survey_question.xml
odoo14_addon_survey_text_question_validation_length-14.0.1.0.1.dev4.dist-info/METADATA
odoo14_addon_survey_text_question_validation_length-14.0.1.0.1.dev4.dist-info/WHEEL
odoo14_addon_survey_text_question_validation_length-14.0.1.0.1.dev4.dist-info/top_level.txt
odoo14_addon_survey_text_question_validation_length-14.0.1.0.1.dev4.dist-info/RECORD
